Metadata-Version: 2.1
Name: curvipy
Version: 1.0.1
Summary: The Python library for making math animations in a few lines of code.
Home-page: https://github.com/dylannalex/curvipy
Author: Dylan Tintenfich
Author-email: tintenfichdylan05@gmail.com
License: MIT
Keywords: curves,linear-algebra,mathematics,animations
Classifier: Programming Language :: Python :: 3.9
Classifier: License :: OSI Approved :: MIT License
License-File: LICENSE
